opp_env/__init__.py
opp_env/__main__.py
opp_env/_version.py
opp_env/opp_env.py
opp_env/database/external.json
opp_env/database/external.py
opp_env/database/inet.py
opp_env/database/omnetpp.py
opp_env/database/simu5g.py
opp_env/database/simulte.py
opp_env/database/testproject.py
opp_env/database/veins.py
opp_env/templates/metadata/startup.bsh
opp_env/templates/workspace/22.11/flake.lock
opp_env/templates/workspace/23.05/flake.lock
opp_env/templates/workspace/24.05/flake.lock
opp_env/templates/workspace/24.11/flake.lock
opp_env/templates/workspace/25.05/flake.lock
opp_env-0.35.0.251114.dist-info/licenses/LICENSE
opp_env-0.35.0.251114.dist-info/METADATA
opp_env-0.35.0.251114.dist-info/WHEEL
opp_env-0.35.0.251114.dist-info/entry_points.txt
opp_env-0.35.0.251114.dist-info/top_level.txt
opp_env-0.35.0.251114.dist-info/RECORD
