Metadata-Version: 2.4
Name: opp_env
Version: 0.35.0.251114
Summary: A tool, that sets up the development environment for OMNeT++ projects
Author-email: András Varga <andras@omnetpp.org>, Levente Mészáros <levy@omnetpp.org>, Rudolf Hornig <rudi@omnetpp.org>
Maintainer-email: Rudolf Hornig <rudi@omnetpp.org>
Project-URL: Homepage, https://omnetpp.org
Project-URL: Documentation, https://github.com/omnetpp/opp_env/blob/main/README.md
Project-URL: Changes, https://github.com/omnetpp/opp_env/blob/main/CHANGES.md
Project-URL: Repository, https://github.com/omnetpp/opp_env
Project-URL: Issues, https://github.com/omnetpp/opp_env/issues
Project-URL: Changelog, https://github.com/omnetpp/opp_env/commits/main
Keywords: omnetpp,omnest,simulation,discrete,event,package manager,model
Classifier: Development Status :: 4 - Beta
Classifier: Operating System :: MacOS
Classifier: Operating System :: POSIX :: Linux
Classifier: Environment :: Console
Classifier: Programming Language :: C++
Classifier: Intended Audience :: Developers
Classifier: Intended Audience :: Science/Research
Classifier: Intended Audience :: Telecommunications Industry
Classifier: Intended Audience :: Education
Classifier: License :: OSI Approved :: GNU Lesser General Public License v3 or later (LGPLv3+)
Classifier: Topic :: Education
Classifier: Topic :: Software Development :: Build Tools
Classifier: Topic :: Software Development :: Libraries
Classifier: Topic :: System :: Software Distribution
Requires-Python: >=3.9
License-File: LICENSE
Dynamic: license-file
